annotator/__init__.py
annotator/__main__.py
annotator/eco/eco.json
chess_annotator-1.1.4.dist-info/LICENSE
chess_annotator-1.1.4.dist-info/METADATA
chess_annotator-1.1.4.dist-info/WHEEL
chess_annotator-1.1.4.dist-info/entry_points.txt
chess_annotator-1.1.4.dist-info/top_level.txt
chess_annotator-1.1.4.dist-info/RECORD
